CHANGES.txt
CONTRIBUTORS.txt
MANIFEST.in
README.md
setup.py
docs/HISTORY.txt
docs/INSTALL.txt
docs/LICENSE.GPL
docs/LICENSE.txt
getpaid/__init__.py
getpaid.pfgbuyableadapter.egg-info/PKG-INFO
getpaid.pfgbuyableadapter.egg-info/SOURCES.txt
getpaid.pfgbuyableadapter.egg-info/dependency_links.txt
getpaid.pfgbuyableadapter.egg-info/entry_points.txt
getpaid.pfgbuyableadapter.egg-info/namespace_packages.txt
getpaid.pfgbuyableadapter.egg-info/not-zip-safe
getpaid.pfgbuyableadapter.egg-info/paster_plugins.txt
getpaid.pfgbuyableadapter.egg-info/requires.txt
getpaid.pfgbuyableadapter.egg-info/top_level.txt
getpaid/pfgbuyableadapter/README.txt
getpaid/pfgbuyableadapter/__init__.py
getpaid/pfgbuyableadapter/config.py
getpaid/pfgbuyableadapter/configure.zcml
getpaid/pfgbuyableadapter/subscriber.py
getpaid/pfgbuyableadapter/content/__init__.py
getpaid/pfgbuyableadapter/content/buyableformadapter.py
getpaid/pfgbuyableadapter/content/configure.zcml
getpaid/pfgbuyableadapter/interfaces/__init__.py
getpaid/pfgbuyableadapter/interfaces/buyableformadapter.py
getpaid/pfgbuyableadapter/profiles/default/factorytool.xml
getpaid/pfgbuyableadapter/profiles/default/metadata.xml
getpaid/pfgbuyableadapter/profiles/default/portlets.xml
getpaid/pfgbuyableadapter/profiles/default/rolemap.xml
getpaid/pfgbuyableadapter/profiles/default/types.xml
getpaid/pfgbuyableadapter/profiles/default/types/Buyable_Form_Adapter.xml
getpaid/pfgbuyableadapter/profiles/default/types/FormFolder.xml
getpaid/pfgbuyableadapter/tests/__init__.py
getpaid/pfgbuyableadapter/tests/base.py
getpaid/pfgbuyableadapter/tests/test_doctest.py