Metadata-Version: 1.0
Name: getpaid.pfgbuyableadapter
Version: 1.0.2
Summary: An adapter for PloneFormGen to allow forms to be purchased.
Home-page: http://github.com/ianderso/getpaid.pfgbuyableadapter
Author: Anderson Leeb Inc
Author-email: admin@andersonleeb.com
License: GPL
Platform: UNKNOWN
Classifier: Framework :: Plone
Classifier: Intended Audience :: Developers
Classifier: License :: OSI Approved :: GNU General Public License (GPL)
